e2xauthoring/__init__.py
e2xauthoring/__version__.py
e2xauthoring/app/__init__.py
e2xauthoring/app/authoring.py
e2xauthoring/app/handlers/apihandlers.py
e2xauthoring/app/handlers/base.py
e2xauthoring/app/handlers/handlers.py
e2xauthoring/app/templates/authoring/asset-manifest.json
e2xauthoring/app/templates/authoring/index.html
e2xauthoring/app/templates/authoring/static/favicon.ico
e2xauthoring/app/templates/authoring/static/js/main.4fa8a886.js
e2xauthoring/app/templates/authoring/static/js/main.4fa8a886.js.LICENSE.txt
e2xauthoring/app/templates/authoring/static/js/main.4fa8a886.js.map
e2xauthoring/assets/.gitignore
e2xauthoring/converters/__init__.py
e2xauthoring/converters/converter.py
e2xauthoring/converters/generateexercise.py
e2xauthoring/dataclasses/__init__.py
e2xauthoring/dataclasses/gitstatus.py
e2xauthoring/dataclasses/jsondataclass.py
e2xauthoring/dataclasses/messages.py
e2xauthoring/dataclasses/pool.py
e2xauthoring/dataclasses/task.py
e2xauthoring/dataclasses/template.py
e2xauthoring/git/__init__.py
e2xauthoring/git/base.py
e2xauthoring/git/factory.py
e2xauthoring/git/gitrepo.py
e2xauthoring/git/utils.py
e2xauthoring/managers/__init__.py
e2xauthoring/managers/assignmentmanager.py
e2xauthoring/managers/base.py
e2xauthoring/managers/presetmanager.py
e2xauthoring/managers/taskmanager.py
e2xauthoring/managers/taskpoolmanager.py
e2xauthoring/managers/templatemanager.py
e2xauthoring/managers/worksheetmanager.py
e2xauthoring/managers/presets/questions/Code (Autograded).ipynb
e2xauthoring/managers/presets/questions/Code (Manual).ipynb
e2xauthoring/managers/presets/questions/Diagram.ipynb
e2xauthoring/managers/presets/questions/Freetext.ipynb
e2xauthoring/managers/presets/questions/Multiple Choice.ipynb
e2xauthoring/managers/presets/questions/Single Choice.ipynb
e2xauthoring/managers/presets/questions/Upload Files.ipynb
e2xauthoring/managers/presets/template/Footer.ipynb
e2xauthoring/managers/presets/template/Group Info.ipynb
e2xauthoring-0.3.1.dist-info/METADATA
e2xauthoring-0.3.1.dist-info/WHEEL
e2xauthoring-0.3.1.dist-info/licenses/LICENSE
e2xauthoring-0.3.1.dist-info/RECORD
