Metadata-Version: 2.4
Name: e2xauthoring
Version: 0.3.1
Summary: Authoring app for e2xgrader
Project-URL: Source, https://github.com/Digiklausur/e2xauthoring
Project-URL: Documentation, https://e2xauthoring.readthedocs.io/en/latest/
Project-URL: Issues, https://github.com/Digiklausur/e2xauthoring/issues
Project-URL: Pypi, https://pypi.org/project/e2xauthoring/
Author-email: Tim Metzler <tim.metzler@h-brs.de>
License-Expression: MIT
License-File: LICENSE
Classifier: Programming Language :: Python
Classifier: Programming Language :: Python :: 3
Classifier: Programming Language :: Python :: 3.7
Classifier: Programming Language :: Python :: 3.8
Classifier: Programming Language :: Python :: 3.9
Requires-Python: >=3.7
Requires-Dist: e2xcore>=0.0.5
Requires-Dist: gitpython
Provides-Extra: dev
Requires-Dist: build; extra == 'dev'
Requires-Dist: hatchling; extra == 'dev'
Requires-Dist: pre-commit; extra == 'dev'
Requires-Dist: pydata-sphinx-theme; extra == 'dev'
Requires-Dist: sphinx; extra == 'dev'
Requires-Dist: tbump; extra == 'dev'
Requires-Dist: twine; extra == 'dev'
